README.md
setup.py
ikea_scaper_project.egg-info/PKG-INFO
ikea_scaper_project.egg-info/SOURCES.txt
ikea_scaper_project.egg-info/dependency_links.txt
ikea_scaper_project.egg-info/requires.txt
ikea_scaper_project.egg-info/top_level.txt
project/__init__.py
project/ikea_scaper.py
project/scraper.py