Metadata-Version: 2.1
Name: ikea-scaper-project
Version: 0.0.3
Summary: Package that allows you to scape data samples from the Ikea website
Home-page: https://github.com/IvanYingX/Ikea-Scraper-Project
Author: Darrel Anderson, Euan Wrigglesworth, Regina Aiken
License: Public Domain Dedication (CC Zero)
Platform: UNKNOWN
